ng_server-1.0.0.data/scripts/server_run
server/__init__.py
server/server.py
server/common/__init__.py
server/common/decorator.py
server/common/descryptors.py
server/common/errors.py
server/common/metaclasses.py
server/common/utils.py
server/common/variables.py
server/server/__init__.py
server/server/add_user.py
server/server/config_window.py
server/server/core.py
server/server/database.py
server/server/main_window.py
server/server/remove_user.py
server/server/stat_window.py
server/unit_tests/__init__.py
server/unit_tests/test_client.py
server/unit_tests/test_utils.py
ng_server-1.0.0.dist-info/METADATA
ng_server-1.0.0.dist-info/WHEEL
ng_server-1.0.0.dist-info/top_level.txt
ng_server-1.0.0.dist-info/RECORD
